MANIFEST.in
README.md
aws_simple_auth.py
requirements.txt
setup.py
app/__init__.py
app/__main__.py
app/clicode.py
app/mfa_auth.py
aws_simple_auth.egg-info/PKG-INFO
aws_simple_auth.egg-info/SOURCES.txt
aws_simple_auth.egg-info/dependency_links.txt
aws_simple_auth.egg-info/entry_points.txt
aws_simple_auth.egg-info/requires.txt
aws_simple_auth.egg-info/top_level.txt