Metadata-Version: 2.1
Name: aws-simple-auth
Version: 0.2.1
Summary: AWS CLI authentication helper to better manage MFA profiles
Home-page: https://gitlab.com/xi0s/aws-simple-auth
Author: Callum Smith
Author-email: callumsmith@me.com
License: MIT
Platform: UNKNOWN
Classifier: Programming Language :: Python :: 3.7
Classifier: Operating System :: OS Independent
Requires-Python: >=3.7
